Workbook

Sheet Dashboard Executivo
A1: XBOX ECOSYSTEM — DASHBOARD EXECUTIVO DE VENDAS
A2: Consolidação e inteligência de mercado: vendas de hardware, software, serviços e performance regional.
A4: RECEITA TOTAL DE VENDAS | D4: UNIDADES VENDIDAS | G4: TICKET MÉDIO POR TRANSAÇÃO | J4: ASSINANTES GAME PASS
A5: =SUM('Vendas Detalhadas'!J8:J100) | D5: =SUM('Vendas Detalhadas'!G8:G100) | G5: =AVERAGE('Vendas Detalhadas'!J8:J100) | J5: =SUM('Serviços e Subscriptions'!E8:E100)
A7: PERFORMANCE CONSOLIDADA POR CATEGORIA DE PRODUTO | H7: PERFORMANCE E SHARE REGIONAL
A8: Categoria de Produto | B8: Origem dos Dados | C8: Unidades Vendidas | D8: Receita Bruta (R$) | E8: Ticket Médio (R$) | F8: Participação (%) | H8: Região / Território | I8: Meta (R$) | J8: Realizado (R$) | K8: Share (%)
A9: Consoles (Hardware) | B9: Vendas Detalhadas | C9: =SUMIFS('Vendas Detalhadas'!G8:G100, 'Vendas Detalhadas'!C8:C100, "Hardware") | D9: =SUMIFS('Vendas Detalhadas'!J8:J100, 'Vendas Detalhadas'!C8:C100, "Hardware") | E9: =D9/C9 | F9: =D9/$D$13 | H9: América do Norte (NA) | I9: 50000000 | J9: 52500000 | K9: =J9/$J$13
A10: Jogos (Games / Software) | B10: Vendas Detalhadas | C10: =SUMIFS('Vendas Detalhadas'!G8:G100, 'Vendas Detalhadas'!C8:C100, "Software") | D10: =SUMIFS('Vendas Detalhadas'!J8:J100, 'Vendas Detalhadas'!C8:C100, "Software") | E10: =D10/C10 | F10: =D10/$D$13 | H10: Europa / UK (EMEA) | I10: 35000000 | J10: 31000000 | K10: =J10/$J$13
A11: Acessórios & Periféricos | B11: Vendas Detalhadas | C11: =SUMIFS('Vendas Detalhadas'!G8:G100, 'Vendas Detalhadas'!C8:C100, "Acessórios") | D11: =SUMIFS('Vendas Detalhadas'!J8:J100, 'Vendas Detalhadas'!C8:C100, "Acessórios") | E11: =D11/C11 | F11: =D11/$D$13 | H11: América Latina (LATAM) | I11: 15000000 | J11: 18200000 | K11: =J11/$J$13
A12: Assinaturas & Serviços (Game Pass) | B12: Serviços e Subscriptions | C12: =SUM('Serviços e Subscriptions'!E8:E100) | D12: =SUM('Serviços e Subscriptions'!F8:F100) | E12: =D12/C12 | F12: =D12/$D$13 | H12: Ásia-Pacífico (APAC) | I12: 20000000 | J12: 16500000 | K12: =J12/$J$13
A13: TOTAL ECOSSISTEMA XBOX | B13: Consolidado Geral | C13: =SUM(C9:C12) | D13: =SUM(D9:D12) | E13: =D13/C13 | F13: =SUM(F9:F12) | H13: TOTAL GLOBAL | I13: =SUM(I9:I12) | J13: =SUM(J9:J12) | K13: =SUM(K9:K12)

Sheet Evolução Mensal
A1: EVOLUÇÃO HISTÓRICA MENSAL DE VENDAS
A7: Mês | B7: Receita Hardware (R$) | C7: Receita Software (R$) | D7: Receita Serviços (R$) | E7: Receita Total (R$)
A8: Jan/2026 | B8: 4500000 | C8: 3200000 | D8: 7100000 | E8: =SUM(B8:D8)
A9: Fev/2026 | B9: 4800000 | C9: 3500000 | D9: 7200000 | E9: =SUM(B9:D9)
A10: Mar/2026 | B10: 5100000 | C10: 3900000 | D10: 7400000 | E10: =SUM(B10:D10)
A11: Abr/2026 | B11: 4900000 | C11: 4100000 | D11: 7600000 | E11: =SUM(B11:D11)
A12: Mai/2026 | B12: 5300000 | C12: 4400000 | D12: 7800000 | E12: =SUM(B12:D12)
A13: Jun/2026 | B13: 5800000 | C13: 5000000 | D13: 8100000 | E13: =SUM(B13:D13)

Sheet Vendas Detalhadas
A1: BASE DE VENDAS BRUTAS — TRANSAÇÕES DETALHADAS
A2: Registro de transações no ecossistema Xbox.
A7: ID Transação | B7: Data Venda | C7: Categoria | D7: SKU / Item | E7: Plataforma / Modelo | F7: Canal de Venda | G7: Qtd Vendida | H7: Preço Unitário (R$) | I7: Desconto (R$) | J7: Receita Total (R$)
A8: TX-1001 | B8: 10/01/2026 | C8: Hardware | D8: Xbox Series X 1TB | E8: Console | F8: Loja Oficial MS | G8: 10 | H8: 4499 | I8: 200 | J8: =(G8*H8)-I8
A9: TX-1002 | B9: 12/01/2026 | C9: Hardware | D9: Xbox Series S 512GB | E9: Console | F9: Varejo Online | G9: 25 | H9: 2699 | I9: 100 | J9: =(G9*H9)-I9
A10: TX-1003 | B10: 15/01/2026 | C10: Software | D10: Starfield Premium Edition | E10: Xbox Series / PC | F10: Xbox Digital Store | G10: 150 | H10: 349 | I10: 0 | J10: =(G10*H10)-I10
A11: TX-1004 | B11: 18/01/2026 | C11: Software | D11: Forza Motorsport | E11: Xbox Series / PC | F11: Xbox Digital Store | G11: 200 | H11: 299 | I11: 15 | J11: =(G11*H11)-I11
A12: TX-1005 | B12: 22/01/2026 | C12: Acessórios | D12: Controle Sem Fio Xbox - Carbon Black | E12: Acessório | F12: Varejo Físico | G12: 80 | H12: 499 | I12: 20 | J12: =(G12*H12)-I12
A13: TX-1006 | B13: 25/01/2026 | C13: Headset Sem Fio Xbox | D13: Acessórios | E13: Acessório | F13: Loja Oficial MS | G13: 40 | H13: 899 | I13: 50 | J13: =(G13*H13)-I13
A100: TOTAL CONSOLIDADO | G100: =SUM(G8:G99) | J100: =SUM(J8:J99)

Sheet Serviços e Subscriptions
A1: RECEITA RECORRENTE DE SERVIÇOS — GAME PASS & CLOUD
A2: Acompanhamento de receita de serviços digitais.
A7: Plano de Assinatura | B7: Região / Mercado | C7: Preço Mensal (R$) | D7: Duração (Meses) | E7: Total Assinantes | F7: Receita Recorrente (R$) | G7: Status / Retenção
A8: Xbox Game Pass Ultimate | B8: Brasil / América Latina | C8: 59.99 | D8: 12 | E8: 120000 | F8: =C8*D8*E8 | G8: Ativo - Alta Retenção
A9: Xbox Game Pass PC | B9: Brasil / América Latina | C9: 35.99 | D9: 12 | E9: 45000 | F9: =C9*D9*E9 | G9: Ativo - Crescimento
A10: Xbox Game Pass Core | B10: Brasil / América Latina | C10: 34.99 | D10: 12 | E10: 30000 | F10: =C10*D10*E10 | G10: Ativo - Estável
A11: Xbox Cloud Gaming (Standalone) | B11: Global | C11: 49.99 | D11: 12 | E11: 15000 | F11: =C11*D11*E11 | G11: Ativo - Expansão
A100: TOTAL CONSOLIDADO | E100: =SUM(E8:E99) | F100: =SUM(F8:F99)

Sheet Hardware & Periféricos
A1: CONTROLE DE ESTOQUE E MARGEM DE HARDWARE
A2: Gestão de custos e margens de hardware.
A7: Modelo / Dispositivo | B7: Cor / Edição Especial | C7: Custo de Fabricação (R$) | D7: Preço de Venda (R$) | E7: Margem Unitária (R$) | F7: Unidades Produzidas | G7: Unidades Vendidas | H7: Estoque Atual
A8: Xbox Series X | B8: Preto Padrão 1TB | C8: 3800 | D8: 4499 | E8: =D8-C8 | F8: 15000 | G8: 12500 | H8: =F8-G8
A9: Xbox Series X | B9: Edição Especial Digital 2TB | C9: 4100 | D9: 4999 | E9: =D9-C9 | F9: 5000 | G9: 4200 | H9: =F9-G9
A10: Xbox Series S | B10: Branco 512GB | C10: 2100 | D10: 2699 | E10: =D10-C10 | F10: 30000 | G10: 28000 | H10: =F10-G10
A11: Xbox Series S | B11: Preto 1TB | C11: 2300 | D11: 2999 | E11: =D11-C11 | F11: 12000 | G11: 9800 | H11: =F11-G11
A12: Controle Elite Series 2 | B12: Preto / Emborrachado | C12: 650 | D12: 1199 | E12: =D12-C12 | F12: 8000 | G12: 6900 | H12: =F12-G12
A100: TOTAL CONSOLIDADO | F100: =SUM(F8:F99) | G100: =SUM(G8:G99) | H100: =SUM(H8:H99)

Sheet Desempenho Regional
A1: DESEMPENHO POR REGIÃO E CUMPRIMENTO DE METAS
A2: Metas e realizados regionais.
A7: Região / Território | B7: Gerente Regional | C7: Meta de Vendas (R$) | D7: Receita Realizada (R$) | E7: Atingimento (%) | F7: Participação no Total (%)
A8: América do Norte (NA) | B8: John Smith | C8: 50000000 | D8: 52500000 | E8: =D8/C8 | F8: =D8/$D$13
A9: Europa / UK (EMEA) | B9: Elena Rostova | C9: 35000000 | D9: 31000000 | E9: =D9/C9 | F9: =D9/$D$13
A10: América Latina (LATAM) | B10: Lucas Padroni | C10: 15000000 | D10: 18200000 | E10: =D10/C10 | F10: =D10/$D$13
A11: Ásia-Pacífico (APAC) | B11: Kenji Sato | C11: 20000000 | D11: 16500000 | E11: =D11/C11 | F11: =D11/$D$13
A100: TOTAL CONSOLIDADO | C100: =SUM(C8:C99) | D100: =SUM(D8:D99)
